{
  "demo": {
    "zero_gauge": {
      "transformation": "Chiral rotation",
      "alpha": 0.2,
      "classical_invariant": true,
      "quantum_invariant": "True",
      "jacobian_magnitude": 0.0,
      "jacobian_phase": 0.0,
      "obstruction_type": "NONE",
      "in_g_scheme": true
    },
    "with_B": {
      "transformation": "Chiral rotation",
      "alpha": 0.2,
      "classical_invariant": true,
      "quantum_invariant": "True",
      "jacobian_magnitude": 0.9999999999999984,
      "jacobian_phase": 1.4394519402461968e-14,
      "obstruction_type": "NONE",
      "in_g_scheme": true
    },
    "phase_scan": {
      "scan_results": [
        {
          "alpha": 0.0,
          "magnitude": 1.0,
          "phase": 0.0,
          "phase_degrees": 0.0
        },
        {
          "alpha": 0.1,
          "magnitude": 1.0000000000000058,
          "phase": -3.647612327840943e-15,
          "phase_degrees": -2.089927916851756e-13
        },
        {
          "alpha": 0.2,
          "magnitude": 1.0000000000000009,
          "phase": -1.5899848608537502e-15,
          "phase_degrees": -9.109942201661534e-14
        },
        {
          "alpha": 0.30000000000000004,
          "magnitude": 0.9999999999999942,
          "phase": -7.248460395068539e-16,
          "phase_degrees": -4.153061886051566e-14
        },
        {
          "alpha": 0.4,
          "magnitude": 1.0000000000000027,
          "phase": -2.4785058125073132e-15,
          "phase_degrees": -1.4200792255531198e-13
        },
        {
          "alpha": 0.5,
          "magnitude": 1.000000000000005,
          "phase": -1.4029278184003673e-15,
          "phase_degrees": -8.038184295583704e-14
        }
      ],
      "phase_slope": -7.549087784725852e-16,
      "is_anomalous": "False",
      "anomaly_coefficient": 0
    },
    "scaling": {
      "scaling_results": [
        {
          "L": 4,
          "N_sites": 16,
          "phase": -3.5821251247500553e-16,
          "magnitude": 1.0000000000000018
        },
        {
          "L": 6,
          "N_sites": 36,
          "phase": -4.982641950772467e-16,
          "magnitude": 1.0000000000000007
        },
        {
          "L": 8,
          "N_sites": 64,
          "phase": 2.290913633983954e-15,
          "magnitude": 1.0000000000000049
        }
      ],
      "is_converging": "False",
      "limiting_phase": 2.290913633983954e-15
    }
  },
  "pymoo": {
    "status": "completed",
    "pareto_front": [
      {
        "B": 0.00021628640787157982,
        "noise": 0.22631210865176976,
        "anomaly_phase": 3.86133465539996e-13,
        "stability": 3.4928437306730142,
        "regularity": 7.585562816274252
      },
      {
        "B": 0.00027469324564749487,
        "noise": 0.1790491933603996,
        "anomaly_phase": 2.4987343583523645e-13,
        "stability": 3.3890740563139716,
        "regularity": 7.3779262336046445
      },
      {
        "B": 0.940755593848015,
        "noise": 0.32782902093012906,
        "anomaly_phase": 7.310807730341505e-14,
        "stability": 2.9936381528956475,
        "regularity": 12.49123564474541
      },
      {
        "B": 0.00027469324564749487,
        "noise": 0.1593840486140895,
        "anomaly_phase": 4.249803476784039e-14,
        "stability": 3.3890740563139614,
        "regularity": 7.377926233604648
      },
      {
        "B": 0.9466212635817115,
        "noise": 0.32770186687864844,
        "anomaly_phase": 3.6373310438751363e-14,
        "stability": 2.609876057385292,
        "regularity": 11.755168715966207
      },
      {
        "B": 0.001079596354791941,
        "noise": 0.22576937334778074,
        "anomaly_phase": 3.4737014298541355e-14,
        "stability": 2.7953382871139794,
        "regularity": 6.189134471970497
      },
      {
        "B": 0.6207349833299911,
        "noise": 0.1757914531756883,
        "anomaly_phase": 3.1410728777743643e-14,
        "stability": 2.522939566151231,
        "regularity": 9.563162654646232
      },
      {
        "B": 0.31670859068468177,
        "noise": 0.3740137195133271,
        "anomaly_phase": 2.876216105147924e-14,
        "stability": 2.755683735329231,
        "regularity": 7.251632214326828
      },
      {
        "B": 0.9480848215695359,
        "noise": 0.32770186687864844,
        "anomaly_phase": 2.4053392863098668e-14,
        "stability": 2.478137392231425,
        "regularity": 11.499594595531866
      },
      {
        "B": 0.002410660408047688,
        "noise": 0.16881596226883594,
        "anomaly_phase": 1.7304367467663934e-14,
        "stability": 2.4475896235310577,
        "regularity": 5.491534797266796
      },
      {
        "B": 0.0041829351226622125,
        "noise": 0.47767429578705906,
        "anomaly_phase": 1.6940370333905915e-14,
        "stability": 2.2097538948440447,
        "regularity": 5.0132208667706415
      },
      {
        "B": 0.3028679636980295,
        "noise": 0.36024082962101056,
        "anomaly_phase": 1.2869928633791466e-14,
        "stability": 2.0887946716232513,
        "regularity": 5.817594093732956
      },
      {
        "B": 0.007086281608213653,
        "noise": 0.18940092303580255,
        "anomaly_phase": 6.191505679837036e-15,
        "stability": 1.9833139591965598,
        "regularity": 4.556399934229854
      },
      {
        "B": 0.009883695279031324,
        "noise": 0.18940092303580255,
        "anomaly_phase": 4.908876203232806e-15,
        "stability": 1.8412476526442478,
        "regularity": 4.2689271822417565
      },
      {
        "B": 0.9673899583782882,
        "noise": 0.2833996856232196,
        "anomaly_phase": 4.256740370297428e-15,
        "stability": 1.826647218074499,
        "regularity": 10.320376231207993
      },
      {
        "B": 0.7860633573576179,
        "noise": 0.1142590304738254,
        "anomaly_phase": 3.553765811353872e-15,
        "stability": 1.2206297332861307,
        "regularity": 8.520190339684662
      },
      {
        "B": 0.37079802423258124,
        "noise": 0.4633824944243009,
        "anomaly_phase": 2.024254978867797e-15,
        "stability": 1.5188077793043004,
        "regularity": 5.20227365356544
      },
      {
        "B": 0.15578514755991407,
        "noise": 0.3981262296493211,
        "anomaly_phase": 8.536825113788853e-16,
        "stability": 0.799698597873631,
        "regularity": 2.70585441317527
      },
      {
        "B": 0.11176632794777575,
        "noise": 0.22576937334778074,
        "anomaly_phase": 4.086089351045863e-17,
        "stability": 0.8916226168008091,
        "regularity": 2.5761975860048576
      },
      {
        "B": 0.12279994363008878,
        "noise": 0.15777072863303795,
        "anomaly_phase": 7.765288293444729e-31,
        "stability": 0.8634390411077718,
        "regularity": 2.5843277992405085
      }
    ]
  }
}