{
  "$schema": "../../../schemas/skill-metadata.schema.json",
  "migrated_from": "SKILL.md frontmatter",
  "migration_date": "2025-12-30",
  "version": "1.0.0",
  "category": "utilities",
  "tags": [
    "presentation",
    "pptx",
    "slides",
    "enterprise",
    "documentation"
  ],
  "author": "ruv",
  "verix-description": [
    "assert|neutral] Enterprise-grade PowerPoint deck generation using evidence-based prompting",
    "workflow enforcement",
    "constraint-based design [ground:given] [conf:0.95] [state:confirmed"
  ],
  "original_directory": "when-creating-presentations-use-pptx-generation",
  "triggers": [
    "creating presentations"
  ]
}
